wsgi_intercept/__init__.py
wsgi_intercept/_urllib3.py
wsgi_intercept/http_client_intercept.py
wsgi_intercept/httplib2_intercept.py
wsgi_intercept/interceptor.py
wsgi_intercept/requests_intercept.py
wsgi_intercept/urllib3_intercept.py
wsgi_intercept/urllib_intercept.py
wsgi_intercept/tests/__init__.py
wsgi_intercept/tests/install.py
wsgi_intercept/tests/test_http_client.py
wsgi_intercept/tests/test_httplib2.py
wsgi_intercept/tests/test_interceptor.py
wsgi_intercept/tests/test_module_interceptor.py
wsgi_intercept/tests/test_requests.py
wsgi_intercept/tests/test_response_headers.py
wsgi_intercept/tests/test_urllib.py
wsgi_intercept/tests/test_urllib3.py
wsgi_intercept/tests/test_wsgi_compliance.py
wsgi_intercept/tests/test_wsgiref.py
wsgi_intercept/tests/wsgi_app.py
wsgi_intercept-1.13.1.dist-info/LICENSE
wsgi_intercept-1.13.1.dist-info/METADATA
wsgi_intercept-1.13.1.dist-info/WHEEL
wsgi_intercept-1.13.1.dist-info/top_level.txt
wsgi_intercept-1.13.1.dist-info/RECORD
