Metadata-Version: 2.1
Name: wsgi_intercept
Version: 1.13.1
Summary: wsgi_intercept installs a WSGI application in place of a real URI for testing.
Home-page: http://pypi.python.org/pypi/wsgi_intercept
Author: Titus Brown, Kumar McMillan, Chris Dent, Sasha Hart
Author-email: cdent@peermore.com
License: MIT License
Classifier: Environment :: Web Environment
Classifier: Intended Audience :: Developers
Classifier: License :: OSI Approved :: MIT License
Classifier: Operating System :: OS Independent
Classifier: Programming Language :: Python :: 2
Classifier: Programming Language :: Python :: 2.7
Classifier: Programming Language :: Python :: 3
Classifier: Programming Language :: Python :: 3.7
Classifier: Programming Language :: Python :: 3.8
Classifier: Programming Language :: Python :: 3.9
Classifier: Programming Language :: Python :: 3.10
Classifier: Programming Language :: Python :: 3.11
Classifier: Programming Language :: Python :: 3.12
Classifier: Topic :: Internet :: WWW/HTTP :: WSGI
Classifier: Topic :: Software Development :: Testing
License-File: LICENSE
Requires-Dist: six
Provides-Extra: testing
Requires-Dist: pytest>=2.4; extra == "testing"
Requires-Dist: httplib2; extra == "testing"
Requires-Dist: requests>=2.0.1; extra == "testing"
Requires-Dist: urllib3<2.0.0,>=1.11.0; extra == "testing"
Provides-Extra: docs
Requires-Dist: sphinx; extra == "docs"
